README.rst
pystatemachine.py
setup.cfg
setup.py
pystatemachine.egg-info/PKG-INFO
pystatemachine.egg-info/SOURCES.txt
pystatemachine.egg-info/dependency_links.txt
pystatemachine.egg-info/top_level.txt