Metadata-Version: 1.1
Name: pystatemachine
Version: 1.1
Summary: Simple Finite-State Machines
Home-page: https://github.com/cmaugg/pystatemachine
Author: Christian Maugg
Author-email: software@christianmaugg.de
License: UNKNOWN
Download-URL: https://github.com/cmaugg/pystatemachine/tarball/1.1
Keywords: state finite-state machine automaton
Platform: UNKNOWN
Classifier: Development Status :: 5 - Production/Stable
Classifier: Intended Audience :: Developers
Classifier: License :: OSI Approved :: MIT License
Classifier: Programming Language :: Python
Classifier: Programming Language :: Python :: 2
Classifier: Programming Language :: Python :: 2.6
Classifier: Programming Language :: Python :: 2.7
Classifier: Programming Language :: Python :: 3
Classifier: Programming Language :: Python :: 3.3
Classifier: Programming Language :: Python :: 3.4
Classifier: Topic :: Software Development :: Libraries
